MANIFEST.in
README.md
README.rst
setup.cfg
setup.py
bcferries/__init__.py
bcferries/abstract.py
bcferries/api.py
bcferries/bcferries.py
bcferries/capacity.py
bcferries/crossing.py
bcferries/decorators.py
bcferries/fuzzydict.py
bcferries/helpers.py
bcferries/route.py
bcferries/scheduled.py
bcferries/terminal.py
bcferries/version.py
bcferries.egg-info/PKG-INFO
bcferries.egg-info/SOURCES.txt
bcferries.egg-info/dependency_links.txt
bcferries.egg-info/requires.txt
bcferries.egg-info/top_level.txt