Metadata-Version: 1.1
Name: bcferries
Version: 0.0.9
Summary: BC Ferries Python Library
Home-page: https://github.com/yasyf/bcferries
Author: Yasyf Mohamedali
Author-email: yasyfm@gmail.com
License: MIT
Download-URL: https://github.com/yasyf/bcferries/tarball/0.0.9
Keywords: bc ferries,schedule
Platform: UNKNOWN
Classifier: License :: OSI Approved :: MIT License
Classifier: Development Status :: 4 - Beta
Classifier: Intended Audience :: Developers
Classifier: Programming Language :: Python :: 2
Classifier: Programming Language :: Python :: 2.6
Classifier: Programming Language :: Python :: 2.7
Classifier: Programming Language :: Python :: 3
Classifier: Programming Language :: Python :: 3.2
Classifier: Programming Language :: Python :: 3.3
Classifier: Programming Language :: Python :: 3.4
